sasmodels/__init__.py
sasmodels/_version.py
sasmodels/alignment.py
sasmodels/bumps_model.py
sasmodels/compare.py
sasmodels/compare_many.py
sasmodels/conversion_table.py
sasmodels/convert.py
sasmodels/core.py
sasmodels/data.py
sasmodels/details.py
sasmodels/direct_model.py
sasmodels/exception.py
sasmodels/generate.py
sasmodels/gengauss.py
sasmodels/guyou.py
sasmodels/jitter.py
sasmodels/kernel.py
sasmodels/kernel_header.c
sasmodels/kernel_iq.c
sasmodels/kernel_template.c
sasmodels/kernelcl.py
sasmodels/kernelcuda.py
sasmodels/kerneldll.py
sasmodels/kernelpy.py
sasmodels/list_pars.py
sasmodels/mixture.py
sasmodels/model_test.py
sasmodels/modelinfo.py
sasmodels/multiscat.py
sasmodels/product.py
sasmodels/resolution.py
sasmodels/resolution2d.py
sasmodels/rst2html.py
sasmodels/sasview_model.py
sasmodels/sesans.py
sasmodels/special.py
sasmodels/weights.py
sasmodels/__pyinstaller/__init__.py
sasmodels/__pyinstaller/hook-sasmodels.py
sasmodels/custom/__init__.py
sasmodels/models/__init__.py
sasmodels/models/_spherepy.py
sasmodels/models/adsorbed_layer.py
sasmodels/models/barbell.c
sasmodels/models/barbell.py
sasmodels/models/bcc_paracrystal.c
sasmodels/models/bcc_paracrystal.py
sasmodels/models/be_polyelectrolyte.py
sasmodels/models/binary_hard_sphere.c
sasmodels/models/binary_hard_sphere.py
sasmodels/models/broad_peak.py
sasmodels/models/capped_cylinder.c
sasmodels/models/capped_cylinder.py
sasmodels/models/core_multi_shell.c
sasmodels/models/core_multi_shell.py
sasmodels/models/core_shell_bicelle.c
sasmodels/models/core_shell_bicelle.py
sasmodels/models/core_shell_bicelle_elliptical.c
sasmodels/models/core_shell_bicelle_elliptical.py
sasmodels/models/core_shell_bicelle_elliptical_belt_rough.c
sasmodels/models/core_shell_bicelle_elliptical_belt_rough.py
sasmodels/models/core_shell_cylinder.c
sasmodels/models/core_shell_cylinder.py
sasmodels/models/core_shell_ellipsoid.c
sasmodels/models/core_shell_ellipsoid.py
sasmodels/models/core_shell_parallelepiped.c
sasmodels-1.0.11.dist-info/METADATA
sasmodels-1.0.11.dist-info/WHEEL
sasmodels-1.0.11.dist-info/entry_points.txt
sasmodels-1.0.11.dist-info/licenses/LICENSE.txt
sasmodels-1.0.11.dist-info/RECORD
