Metadata-Version: 2.4
Name: sasmodels
Version: 1.0.11
Summary: SasModels small-angle scattering modelling
Project-URL: Homepage, http://sasview.org
Project-URL: Documentation, https://www.sasview.org/docs/user/qtgui/Perspectives/Fitting/models/index.html
Project-URL: Repository, https://github.com/SasView/sasmodels/
Project-URL: Issues, https://github.com/SasView/sasmodels/issues
Project-URL: Changelog, https://github.com/SasView/sasmodels/blob/master/CHANGES.rst
Author-email: SasView Team <developers@sasview.org>
License: Public domain
License-File: LICENSE.txt
Keywords: X-ray,data analysis,neutron,scattering,small-angle
Classifier: Development Status :: 4 - Beta
Classifier: Environment :: Console
Classifier: Intended Audience :: Science/Research
Classifier: License :: Public Domain
Classifier: Operating System :: OS Independent
Classifier: Programming Language :: C
Classifier: Programming Language :: Python
Classifier: Topic :: Scientific/Engineering
Classifier: Topic :: Scientific/Engineering :: Chemistry
Classifier: Topic :: Scientific/Engineering :: Physics
Requires-Python: >=3.9
Requires-Dist: bumps
Requires-Dist: columnize
Requires-Dist: matplotlib
Requires-Dist: numpy
Requires-Dist: scipy
Requires-Dist: siphash24
Requires-Dist: tccbox
Provides-Extra: cuda
Requires-Dist: pycuda; extra == 'cuda'
Provides-Extra: docs
Requires-Dist: docutils; extra == 'docs'
Requires-Dist: siphash24; extra == 'docs'
Requires-Dist: sphinx; extra == 'docs'
Provides-Extra: opencl
Requires-Dist: pyopencl; extra == 'opencl'
Provides-Extra: server
Provides-Extra: test
Requires-Dist: docutils; extra == 'test'
Requires-Dist: pytest; extra == 'test'
Requires-Dist: unittest-xml-reporting; extra == 'test'
